setup.py
ansunit/__init__.py
ansunit.egg-info/PKG-INFO
ansunit.egg-info/SOURCES.txt
ansunit.egg-info/dependency_links.txt
ansunit.egg-info/entry_points.txt
ansunit.egg-info/requires.txt
ansunit.egg-info/top_level.txt