Metadata-Version: 1.0
Name: ansunit
Version: 0.1.7
Summary: Declarative unit testing for answer set programming projects
Home-page: https://github.com/rndmcnlly/ansunit
Author: Adam M. Smith
Author-email: adam@adamsmith.as
License: MIT
Platform: UNKNOWN
